{
  "language": "de",
  "phase": 6,
  "title": "Writing · Trace",
  "lessons": [
    {
      "id": "de-p6-l1",
      "title": "Großbuchstaben",
      "type": "trace",
      "maxPoints": 100,
      "items": [
        {
          "glyph": "A",
          "name": "trace"
        },
        {
          "glyph": "B",
          "name": "trace"
        },
        {
          "glyph": "C",
          "name": "trace"
        },
        {
          "glyph": "D",
          "name": "trace"
        },
        {
          "glyph": "E",
          "name": "trace"
        },
        {
          "glyph": "F",
          "name": "trace"
        },
        {
          "glyph": "G",
          "name": "trace"
        },
        {
          "glyph": "H",
          "name": "trace"
        },
        {
          "glyph": "I",
          "name": "trace"
        },
        {
          "glyph": "J",
          "name": "trace"
        },
        {
          "glyph": "K",
          "name": "trace"
        },
        {
          "glyph": "L",
          "name": "trace"
        },
        {
          "glyph": "M",
          "name": "trace"
        }
      ],
      "quiz": []
    },
    {
      "id": "de-p6-l2",
      "title": "Großbuchstaben 2",
      "type": "trace",
      "maxPoints": 100,
      "items": [
        {
          "glyph": "N",
          "name": "trace"
        },
        {
          "glyph": "O",
          "name": "trace"
        },
        {
          "glyph": "P",
          "name": "trace"
        },
        {
          "glyph": "Q",
          "name": "trace"
        },
        {
          "glyph": "R",
          "name": "trace"
        },
        {
          "glyph": "S",
          "name": "trace"
        },
        {
          "glyph": "T",
          "name": "trace"
        },
        {
          "glyph": "U",
          "name": "trace"
        },
        {
          "glyph": "V",
          "name": "trace"
        },
        {
          "glyph": "W",
          "name": "trace"
        },
        {
          "glyph": "X",
          "name": "trace"
        },
        {
          "glyph": "Y",
          "name": "trace"
        },
        {
          "glyph": "Z",
          "name": "trace"
        }
      ],
      "quiz": []
    },
    {
      "id": "de-p6-l3",
      "title": "Umlaute & ß",
      "type": "trace",
      "maxPoints": 100,
      "items": [
        {
          "glyph": "Ä",
          "name": "trace"
        },
        {
          "glyph": "Ö",
          "name": "trace"
        },
        {
          "glyph": "Ü",
          "name": "trace"
        },
        {
          "glyph": "ß",
          "name": "trace"
        },
        {
          "glyph": "ä",
          "name": "trace"
        },
        {
          "glyph": "ö",
          "name": "trace"
        },
        {
          "glyph": "ü",
          "name": "trace"
        }
      ],
      "quiz": []
    },
    {
      "id": "de-p6-l4",
      "title": "Wörter",
      "type": "trace",
      "maxPoints": 100,
      "items": [
        {
          "glyph": "Hund",
          "name": "trace"
        },
        {
          "glyph": "Katze",
          "name": "trace"
        },
        {
          "glyph": "Apfel",
          "name": "trace"
        },
        {
          "glyph": "Sonne",
          "name": "trace"
        },
        {
          "glyph": "Baum",
          "name": "trace"
        }
      ],
      "quiz": []
    }
  ]
}